Workbook

Sheet Dashboard
A1: PERSONAL BUDGET MANAGEMENT SYSTEM
A4: TOTAL INCOME | D4: TOTAL EXPENSES | G4: TOTAL SAVINGS | J4: SAVINGS RATE
A5: =SUMIF(Transactions!$B$2:$B$1000,"Income",Transactions!$E$2:$E$1000) -> 113000 | D5: =SUMIF(Transactions!$B$2:$B$1000,"Expense",Transactions!$E$2:$E$1000) -> 48600 | G5: =A5-D5 -> 64400 | J5: =IF(A5=0,0,G5/A5) -> 0.5699115
A54: Update the Transactions sheet to add records. Summary formulas and charts use transaction data; use Excel Data > Refresh All if applicable. Edit monthly limits in Budget Plan.

Sheet Transactions
A1: Date | B1: Type | C1: Category | D1: Description | E1: Amount | F1: Payment Mode
A2: 46266 | B2: Income | C2: Salary | D2: Monthly Salary | E2: 50000 | F2: Bank
A3: 46267 | B3: Expense | C3: Food | D3: Groceries | E3: 3500 | F3: UPI
A4: 46269 | B4: Expense | C4: Transport | D4: Bus and Auto | E4: 1500 | F4: UPI
A5: 46271 | B5: Expense | C5: Rent | D5: House Rent | E5: 12000 | F5: Bank
A6: 46273 | B6: Expense | C6: Shopping | D6: Clothes | E6: 2500 | F6: Card
A7: 46275 | B7: Expense | C7: Entertainment | D7: Movie | E7: 800 | F7: UPI
A8: 46277 | B8: Expense | C8: Bills | D8: Electricity Bill | E8: 1800 | F8: UPI
A9: 46280 | B9: Income | C9: Freelance | D9: Freelance Work | E9: 8000 | F9: Bank
A10: 46283 | B10: Expense | C10: Food | D10: Restaurant | E10: 1200 | F10: UPI
A11: 46285 | B11: Expense | C11: Health | D11: Medicines | E11: 700 | F11: UPI
A12: 46287 | B12: Expense | C12: Transport | D12: Fuel | E12: 2500 | F12: Card
A13: 46290 | B13: Expense | C13: Shopping | D13: Household Items | E13: 1500 | F13: UPI
... A21: 46301 | B21: Expense | C21: Entertainment | D21: Movie | E21: 600 | F21: UPI

Sheet Income
A1: Date | B1: Source | C1: Category | D1: Amount
A2: 46266 | B2: Company | C2: Salary | D2: 50000
A3: 46280 | B3: Freelance Client | C3: Freelance | D3: 8000
A4: 46294 | B4: Company | C4: Bonus | D4: 5000
A5: 46296 | B5: Company | C5: Salary | D5: 50000

Sheet Expense
A1: Date | B1: Category | C1: Description | D1: Amount
A2: 46267 | B2: Food | C2: Groceries | D2: 3500
A3: 46269 | B3: Transport | C3: Bus and Auto | D3: 1500
A4: 46271 | B4: Rent | C4: House Rent | D4: 12000
A5: 46273 | B5: Shopping | C5: Clothes | D5: 2500
A6: 46275 | B6: Entertainment | C6: Movie | D6: 800
A7: 46277 | B7: Bills | C7: Electricity Bill | D7: 1800
A8: 46283 | B8: Food | C8: Restaurant | D8: 1200
A9: 46285 | B9: Health | C9: Medicines | D9: 700
A10: 46287 | B10: Transport | C10: Fuel | D10: 2500
A11: 46290 | B11: Shopping | C11: Household Items | D11: 1500
A12: 46292 | B12: Bills | C12: Internet Bill | D12: 900
A13: 46297 | B13: Rent | C13: House Rent | D13: 12000
... A17: 46301 | B17: Entertainment | C17: Movie | D17: 600

Sheet Monthly Summary
A1: Month | B1: Income | C1: Expense | D1: Savings | E1: Savings %
A2: September 2026 | B2: 63000 | C2: 28900 | D2: =B2-C2 -> 34100 | E2: =IF(B2=0,0,D2/B2) -> 0.54126984
A3: October 2026 | B3: 50000 | C3: 19700 | D3: =B3-C3 -> 30300 | E3: =IF(B3=0,0,D3/B3) -> 0.606

Sheet Categories
A1: Category | B1: Type
A2: Salary | B2: Income
A3: Freelance | B3: Income
A4: Bonus | B4: Income
A5: Food | B5: Expense
A6: Transport | B6: Expense
A7: Rent | B7: Expense
A8: Shopping | B8: Expense
A9: Entertainment | B9: Expense
A10: Bills | B10: Expense
A11: Health | B11: Expense
A12: Education | B12: Expense
A13: Other | B13: Expense

Sheet Saving Tracker
A1: Month | B1: Goal | C1: Actual Savings | D1: Status
A2: September 2026 | B2: 30000 | C2: 34100 | D2: =IF(C2>=B2,"Achieved","Not Achieved") -> Achieved
A3: October 2026 | B3: 30000 | C3: 30300 | D3: =IF(C3>=B3,"Achieved","Not Achieved") -> Achieved

Sheet Project Overview
A1: BUDGET MANAGEMENT SYSTEM - PROJECT OVERVIEW
A3: Project Objective | B3: A web-based dashboard that reads Excel data, tracks income and expenses, calculates savings, and provides monthly analysis.
A4: Frontend | B4: Streamlit
A5: Backend | B5: Python
A6: Analysis | B6: Pandas
A7: Charts | B7: Plotly + Matplotlib
A8: Database | B8: Excel Workbook
A9: IDE | B9: PyCharm
A10: Main Features | B10: Income tracking, expense tracking, savings calculation, category analysis, monthly trends and dashboard.

Sheet Chart Data
A1: Month | B1: Income | C1: Expenses | D1: Savings | E1: Category | F1: Expense Amount | G1: Budget | H1: Actual | I1: Income Source | J1: Income Amount | K1: Payment Mode | L1: Payment Amount
A2: September 2026 | B2: =SUMIFS(Transactions!$E$2:$E$1000,Transactions!$B$2:$B$1000,"Income",Transactions!$A$2:$A$1000,">="&DATEVALUE("1 "&A2),Transactions!$A$2:$A$1000,"<"&EDATE(DATEVALUE("1 "&A2),1)) -> 63000 | C2: =SUMIFS(Transactions!$E$2:$E$1000,Transactions!$B$2:$B$1000,"Expense",Transactions!$A$2:$A$1000,">="&DATEVALUE("1 "&A2),Transactions!$A$2:$A$1000,"<"&EDATE(DATEVALUE("1 "&A2),1)) -> 28900 | D2: =B2-C2 -> 34100 | E2: Food | F2: =SUMIFS(Transactions!$E$2:$E$1000,Transactions!$B$2:$B$1000,"Expense",Transactions!$C$2:$C$1000,E2) -> 7900 | G2: ='Budget Plan'!B2 -> 5000 | H2: ='Budget Plan'!C2 -> 7900 | I2: Company | J2: =SUMIF(Income!$B$2:$B$1000,I2,Income!$D$2:$D$1000) -> 105000 | K2: Bank | L2: =SUMIFS(Transactions!$E$2:$E$1000,Transactions!$B$2:$B$1000,"Expense",Transactions!$F$2:$F$1000,K2) -> 24000
A3: October 2026 | B3: =SUMIFS(Transactions!$E$2:$E$1000,Transactions!$B$2:$B$1000,"Income",Transactions!$A$2:$A$1000,">="&DATEVALUE("1 "&A3),Transactions!$A$2:$A$1000,"<"&EDATE(DATEVALUE("1 "&A3),1)) -> 50000 | C3: =SUMIFS(Transactions!$E$2:$E$1000,Transactions!$B$2:$B$1000,"Expense",Transactions!$A$2:$A$1000,">="&DATEVALUE("1 "&A3),Transactions!$A$2:$A$1000,"<"&EDATE(DATEVALUE("1 "&A3),1)) -> 19700 | D3: =B3-C3 -> 30300 | E3: Transport | F3: =SUMIFS(Transactions!$E$2:$E$1000,Transactions!$B$2:$B$1000,"Expense",Transactions!$C$2:$C$1000,E3) -> 6200 | G3: ='Budget Plan'!B3 -> 3000 | H3: ='Budget Plan'!C3 -> 6200 | I3: Freelance Client | J3: =SUMIF(Income!$B$2:$B$1000,I3,Income!$D$2:$D$1000) -> 8000 | K3: UPI | L3: =SUMIFS(Transactions!$E$2:$E$1000,Transactions!$B$2:$B$1000,"Expense",Transactions!$F$2:$F$1000,K3) -> 17400
E4: Rent | F4: =SUMIFS(Transactions!$E$2:$E$1000,Transactions!$B$2:$B$1000,"Expense",Transactions!$C$2:$C$1000,E4) -> 24000 | G4: ='Budget Plan'!B4 -> 12000 | H4: ='Budget Plan'!C4 -> 24000 | K4: Card | L4: =SUMIFS(Transactions!$E$2:$E$1000,Transactions!$B$2:$B$1000,"Expense",Transactions!$F$2:$F$1000,K4) -> 7200
E5: Shopping | F5: =SUMIFS(Transactions!$E$2:$E$1000,Transactions!$B$2:$B$1000,"Expense",Transactions!$C$2:$C$1000,E5) -> 4000 | G5: ='Budget Plan'!B5 -> 3000 | H5: ='Budget Plan'!C5 -> 4000
E6: Entertainment | F6: =SUMIFS(Transactions!$E$2:$E$1000,Transactions!$B$2:$B$1000,"Expense",Transactions!$C$2:$C$1000,E6) -> 1400 | G6: ='Budget Plan'!B6 -> 2000 | H6: ='Budget Plan'!C6 -> 1400
E7: Bills | F7: =SUMIFS(Transactions!$E$2:$E$1000,Transactions!$B$2:$B$1000,"Expense",Transactions!$C$2:$C$1000,E7) -> 4400 | G7: ='Budget Plan'!B7 -> 4000 | H7: ='Budget Plan'!C7 -> 4400
E8: Health | F8: =SUMIFS(Transactions!$E$2:$E$1000,Transactions!$B$2:$B$1000,"Expense",Transactions!$C$2:$C$1000,E8) -> 700 | G8: ='Budget Plan'!B8 -> 1500 | H8: ='Budget Plan'!C8 -> 700
E9: Education | F9: =SUMIFS(Transactions!$E$2:$E$1000,Transactions!$B$2:$B$1000,"Expense",Transactions!$C$2:$C$1000,E9) -> 0 | G9: ='Budget Plan'!B9 -> 2000 | H9: ='Budget Plan'!C9 -> 0
E10: Other | F10: =SUMIFS(Transactions!$E$2:$E$1000,Transactions!$B$2:$B$1000,"Expense",Transactions!$C$2:$C$1000,E10) -> 0 | G10: ='Budget Plan'!B10 -> 2000 | H10: ='Budget Plan'!C10 -> 0

Sheet Budget Plan
A1: Category | B1: Monthly Budget | C1: Actual Expenses | D1: Remaining Budget
A2: Food | B2: 5000 | C2: =SUMIFS(Transactions!$E$2:$E$1000,Transactions!$B$2:$B$1000,"Expense",Transactions!$C$2:$C$1000,A2) -> 7900 | D2: =B2-C2 -> -2900
A3: Transport | B3: 3000 | C3: =SUMIFS(Transactions!$E$2:$E$1000,Transactions!$B$2:$B$1000,"Expense",Transactions!$C$2:$C$1000,A3) -> 6200 | D3: =B3-C3 -> -3200
A4: Rent | B4: 12000 | C4: =SUMIFS(Transactions!$E$2:$E$1000,Transactions!$B$2:$B$1000,"Expense",Transactions!$C$2:$C$1000,A4) -> 24000 | D4: =B4-C4 -> -12000
A5: Shopping | B5: 3000 | C5: =SUMIFS(Transactions!$E$2:$E$1000,Transactions!$B$2:$B$1000,"Expense",Transactions!$C$2:$C$1000,A5) -> 4000 | D5: =B5-C5 -> -1000
A6: Entertainment | B6: 2000 | C6: =SUMIFS(Transactions!$E$2:$E$1000,Transactions!$B$2:$B$1000,"Expense",Transactions!$C$2:$C$1000,A6) -> 1400 | D6: =B6-C6 -> 600
A7: Bills | B7: 4000 | C7: =SUMIFS(Transactions!$E$2:$E$1000,Transactions!$B$2:$B$1000,"Expense",Transactions!$C$2:$C$1000,A7) -> 4400 | D7: =B7-C7 -> -400
A8: Health | B8: 1500 | C8: =SUMIFS(Transactions!$E$2:$E$1000,Transactions!$B$2:$B$1000,"Expense",Transactions!$C$2:$C$1000,A8) -> 700 | D8: =B8-C8 -> 800
A9: Education | B9: 2000 | C9: =SUMIFS(Transactions!$E$2:$E$1000,Transactions!$B$2:$B$1000,"Expense",Transactions!$C$2:$C$1000,A9) -> 0 | D9: =B9-C9 -> 2000
A10: Other | B10: 2000 | C10: =SUMIFS(Transactions!$E$2:$E$1000,Transactions!$B$2:$B$1000,"Expense",Transactions!$C$2:$C$1000,A10) -> 0 | D10: =B10-C10 -> 2000
